deltascf_aims/__init__.py
deltascf_aims/calc_dscf.py
deltascf_aims/cli.py
deltascf_aims/core.py
deltascf_aims/force_occupation.py
deltascf_aims/main.py
deltascf_aims/new_cli.py
deltascf_aims/plot.py
deltascf_aims/schmid_pseudo_voigt.py
deltascf_aims/test/control.in
deltascf_aims/test/geometry.in
deltascf_aims/test/geometry_no_fc.in
deltascf_aims/test/ground/aims.out
deltascf_aims/test/ground/control.in
deltascf_aims/test/ground/control.in.new
deltascf_aims/test/ground/geometry.in
deltascf_aims/test/ground/slurm-10189012.out
deltascf_aims/utils/__init__.py
deltascf_aims/utils/add_basis_functions.yml
deltascf_aims/utils/calculations_utils.py
deltascf_aims/utils/checks_utils.py
deltascf_aims/utils/click_extras.py
deltascf_aims/utils/control_utils.py
deltascf_aims/utils/elements.yml
deltascf_aims/utils/geometry_utils.py
deltascf_aims/utils/hints.py
deltascf_aims-1.1.5.dist-info/METADATA
deltascf_aims-1.1.5.dist-info/WHEEL
deltascf_aims-1.1.5.dist-info/entry_points.txt
deltascf_aims-1.1.5.dist-info/licenses/LICENSE
deltascf_aims-1.1.5.dist-info/RECORD
