Metadata-Version: 2.4
Name: deltascf-aims
Version: 1.1.5
Summary: Application to calculate core holes in FHI-aims
Project-URL: Repository, https://github.com/maurergroup/deltascf-aims
Author-email: Dylan Morgan <dylan.morgan@warwick.ac.uk>
License-File: LICENSE
Requires-Python: <3.15,>=3.10
Requires-Dist: ase==3.22.1
Requires-Dist: click>=8.1.7
Requires-Dist: matplotlib>=3.9.2
Requires-Dist: numpy>=2
Requires-Dist: pyyaml>=6.0.2
